xspharm/__init__.py
xspharm/xspharm.py
xspharm-0.1.2.dist-info/AUTHORS.rst
xspharm-0.1.2.dist-info/LICENSE
xspharm-0.1.2.dist-info/METADATA
xspharm-0.1.2.dist-info/WHEEL
xspharm-0.1.2.dist-info/top_level.txt
xspharm-0.1.2.dist-info/RECORD
