Metadata-Version: 2.1
Name: xspharm
Version: 0.1.2
Summary: xarray interface to spherical harmonic transform
Home-page: https://github.com/senclimate/xspharm
Author: Sen Zhao
Author-email: zhaos2016@gmail.com
License: BSD license
Keywords: xspharm
Classifier: Development Status :: 2 - Pre-Alpha
Classifier: Intended Audience :: Developers
Classifier: License :: OSI Approved :: BSD License
Classifier: Natural Language :: English
Classifier: Programming Language :: Python :: 3
Classifier: Programming Language :: Python :: 3.6
Classifier: Programming Language :: Python :: 3.7
Classifier: Programming Language :: Python :: 3.8
Requires-Python: >=3.6
License-File: LICENSE
License-File: AUTHORS.rst
Requires-Dist: numpy
Requires-Dist: xarray
Requires-Dist: pyspharm >=1.0.9
